stormloader
