Metadata-Version: 1.1
Name: stormloader
Version: 1.7.3
Summary: A utility for interacting with the Storm mote
Home-page: https://github.com/SoftwareDefinedBuildings/stormloader
Author: Michael P Andersen
Author-email: m.andersen@cs.berkeley.edu
License: UNKNOWN
Download-URL: https://github.com/SoftwareDefinedBuildings/stormloader/tarball/1.2
Keywords: storm,mote,bootloader
Platform: UNKNOWN
